docscov/__init__.py
docscov-1.1.3.dist-info/LICENSE
docscov-1.1.3.dist-info/METADATA
docscov-1.1.3.dist-info/WHEEL
docscov-1.1.3.dist-info/top_level.txt
docscov-1.1.3.dist-info/RECORD
