Metadata-Version: 2.1
Name: docscov
Version: 1.1.3
Summary: Sphinx extension to make a dynamic documentation coverage badge
Home-page: https://gitlab.com/AkibAzmain/docscov
Author: Akib Azmain
Author-email: akib8492@gmail.com
License: UNKNOWN
Platform: UNKNOWN
Classifier: Programming Language :: Python :: 3
Classifier: License :: OSI Approved :: GNU General Public License v3 (GPLv3)
Classifier: Operating System :: OS Independent
Requires-Python: >=3.8
Requires-Dist: coverxygen
Requires-Dist: sphinx
